[
  {
    "name": "IDK Yet",
    "members": ["gen / pekoraali", "BlocknBoom! [⚡61]", "S!ence", "Prrin"]
  },
  {
    "name": "Venatus Games",
    "members": ["Jack", "Argo Daddy", "Shawnx17", "Fuzzle34"]
  },
  {
    "name": "[X]odoku_3a_nuB0M",
    "members": ["PyjamSy / DoomerCy", "Just Satanya", "AG6x3", "srnk / gordy", "skin2000 (Reserve)"]
  },
  {
    "name": "Superteam 2: Eletric Boogaloo",
    "members": ["Arnet", "Coco", "deWolf", "Dodo Sandvich"]
  },
  {
    "name": "The Infierior Team",
    "members": ["Tank", "Satisfied Onion", "d3nk", "Foralux"]
  },
  {
    "name": "Individuals",
    "members": ["CrêpeXI", "Samson1", "Bence", "Milky Way", "tTulonatotal", "pink little pig", "No_Luke_No_Life_No_Lazy"]
  }
]